bigram_spam_classifier/__init__.py
bigram_spam_classifier/spamclassifier.py
bigram_spam_classifier/data/spam_collection.csv
bigram_spam_classifier-0.0.6.dist-info/LICENSE
bigram_spam_classifier-0.0.6.dist-info/METADATA
bigram_spam_classifier-0.0.6.dist-info/WHEEL
bigram_spam_classifier-0.0.6.dist-info/top_level.txt
bigram_spam_classifier-0.0.6.dist-info/RECORD
