Metadata-Version: 2.1
Name: bigram-spam-classifier
Version: 0.0.6
Summary: A bigram approach for classifying Spam and Ham messages
Home-page: https://github.com/Kabilesh93/bigram-spam-classifier
Author: Kabilesh
Author-email: 
License: UNKNOWN
Platform: UNKNOWN
Classifier: Programming Language :: Python :: 3
Classifier: License :: OSI Approved :: MIT License
Classifier: Operating System :: OS Independent
Requires-Dist: nltk
Requires-Dist: pandas
